pie4t/__init__.py
pie4t/__init__ori.py
pie4t/assist.py
pie4t/box.py
pie4t/circle.py
pie4t/common.py
pie4t/engine.py
pie4t/physics_common.py
pie4t/repl.py
pie4t/segment.py
pie4t/wrapper.py
物理模組/__init__.py
pie4t-0.1.0.dist-info/LICENSE
pie4t-0.1.0.dist-info/METADATA
pie4t-0.1.0.dist-info/WHEEL
pie4t-0.1.0.dist-info/top_level.txt
pie4t-0.1.0.dist-info/RECORD
