Metadata-Version: 2.1
Name: pie4t
Version: 0.1.0
Summary: Physics Impulse Engine wrapper library for Teenagers
Home-page: https://github.com/beardad1975/pie4t
Author: Wen-Hung, Chang 張文宏
Author-email: beardad1975@nmes.tyc.edu.tw
Platform: Windows
Classifier: Programming Language :: Python :: 3
Classifier: License :: OSI Approved :: MIT License
Classifier: Operating System :: Microsoft :: Windows
Classifier: Natural Language :: Chinese (Traditional)
Requires-Python: >=3.8
License-File: LICENSE
Requires-Dist: arcade (~=2.6.0)
Requires-Dist: pymunk (~=6.4.0)
